{
  "measurement_duration": 640,
  "motor_timeout": 8,
  "chart_update_interval": 3,
  "track_visibility": {
    "Acetaldehyde (CH\u2083CHO)": true,
    "Ammonia (NH\u2083)": true,
    "Carbon Dioxide (CO\u2082)": false,
    "Carbon Monoxide (CO)": true,
    "Ethanol (C\u2082H\u2085OH)": true,
    "Methane (CH\u2084)": true,
    "Methanol (CH\u2083OH)": true,
    "Nitrous Oxide (N\u2082O)": true,
    "Oxygen (O\u2082)": false,
    "Sulfur Dioxide (SO\u2082)": true,
    "Water Vapor (H\u2082O)": false
  }
}